testjx/__init__.py
testjx/testjx.py
testjx-0.0.1.dist-info/LICENSE.txt
testjx-0.0.1.dist-info/METADATA
testjx-0.0.1.dist-info/WHEEL
testjx-0.0.1.dist-info/top_level.txt
testjx-0.0.1.dist-info/RECORD
